{"schema":{"namespace":"Template.Data","alias":"Self","annotation:UseStrongSpatialTypes":"false","xmlns:annotation":"http://schemas.microsoft.com/ado/2009/02/edm/annotation","xmlns:customannotation":"http://schemas.microsoft.com/ado/2013/11/edm/customannotation","xmlns":"http://schemas.microsoft.com/ado/2009/11/edm","cSpaceOSpaceMapping":"[[\"Template.Data.User\",\"Template.Data.User\"]]","entityType":{"name":"User","customannotation:ClrType":"Template.Data.User, Template.Data, Version=1.0.0.0, Culture=neutral, PublicKeyToken=null","key":{"propertyRef":{"name":"Id"}},"property":[{"name":"Id","type":"Edm.Int64","nullable":"false","annotation:StoreGeneratedPattern":"Identity"},{"name":"UserName","type":"Edm.String","maxLength":"100","fixedLength":"false","unicode":"false","nullable":"false"},{"name":"FirstName","type":"Edm.String","maxLength":"100","fixedLength":"false","unicode":"false","nullable":"false"},{"name":"LastName","type":"Edm.String","maxLength":"100","fixedLength":"false","unicode":"false","nullable":"false"},{"name":"Email","type":"Edm.String","maxLength":"100","fixedLength":"false","unicode":"false","nullable":"false"},{"name":"RowVersion","type":"Edm.Decimal","precision":"19","scale":"4","nullable":"false"},{"name":"CreatedBy","type":"Edm.String","maxLength":"100","fixedLength":"false","unicode":"false","nullable":"false"},{"name":"CreatedByUserId","type":"Edm.Int64","nullable":"false"},{"name":"CreatedDate","type":"Edm.DateTime","nullable":"false"},{"name":"ModifiedBy","type":"Edm.String","maxLength":"100","fixedLength":"false","unicode":"false","nullable":"false"},{"name":"ModifiedByUserId","type":"Edm.Int64","nullable":"false"},{"name":"ModifiedDate","type":"Edm.DateTime","nullable":"false"}]},"entityContainer":{"name":"TemplateContext","customannotation:UseClrTypes":"true","entitySet":{"name":"Users","entityType":"Self.User"}}}}